{
	"configurations" : 
	[
		{
			"directories" : 
			[
				{
					"build" : ".",
					"childIndexes" : 
					[
						1,
						2
					],
					"hasInstallRule" : true,
					"minimumCMakeVersion" : 
					{
						"string" : "3.8"
					},
					"projectIndex" : 0,
					"source" : "."
				},
				{
					"build" : "I2C",
					"hasInstallRule" : true,
					"minimumCMakeVersion" : 
					{
						"string" : "3.8"
					},
					"parentIndex" : 0,
					"projectIndex" : 0,
					"source" : "I2C",
					"targetIndexes" : 
					[
						1
					]
				},
				{
					"build" : "BMX055",
					"hasInstallRule" : true,
					"minimumCMakeVersion" : 
					{
						"string" : "3.8"
					},
					"parentIndex" : 0,
					"projectIndex" : 0,
					"source" : "BMX055",
					"targetIndexes" : 
					[
						0
					]
				}
			],
			"name" : "Debug",
			"projects" : 
			[
				{
					"directoryIndexes" : 
					[
						0,
						1,
						2
					],
					"name" : "I2CDevices",
					"targetIndexes" : 
					[
						0,
						1
					]
				}
			],
			"targets" : 
			[
				{
					"directoryIndex" : 2,
					"id" : "BMX055::@83f7bf8e4d657e835f6f",
					"jsonFile" : "target-BMX055-Debug-e6c0ea86174ec2ec1c2e.json",
					"name" : "BMX055",
					"projectIndex" : 0
				},
				{
					"directoryIndex" : 1,
					"id" : "I2C::@8d172014f33441714be8",
					"jsonFile" : "target-I2C-Debug-c1280e9736ae02d36286.json",
					"name" : "I2C",
					"projectIndex" : 0
				}
			]
		}
	],
	"kind" : "codemodel",
	"paths" : 
	{
		"build" : "C:/Users/Onogi/source/repos/I2CDevices/out/build/x64-Debug (default)",
		"source" : "C:/Users/Onogi/source/repos/I2CDevices"
	},
	"version" : 
	{
		"major" : 2,
		"minor" : 0
	}
}
